[{"company":"Hammes and Sons","position":"Sales Representative","status":"selected","offer":24,"jobType":"Full-Time","jobLocation":"Krasnystaw","createdAt":"2022-08-12T13:03:35Z","createdBy":"6368c8a6b397bb7ad67fde5b"},
{"company":"Huel, Kuhic and Kulas","position":"Speech Pathologist","status":"selected","offer":27,"jobType":"Full-Time + Internship","jobLocation":"Argel","createdAt":"2022-03-29T06:10:04Z","createdBy":"6368c8a6b397bb7ad67fde5b"},
{"company":"Bartell, Feeney and Brown","position":"Senior Editor","status":"pending","offer":23,"jobType":"Internship","jobLocation":"Kumanis","createdAt":"2022-09-01T09:03:11Z","createdBy":"6368c8a6b397bb7ad67fde5b"},
{"company":"Ruecker, Fritsch and Prosacco","position":"Financial Advisor","status":"pending","offer":3,"jobType":"Full-Time","jobLocation":"Netrakona","createdAt":"2022-07-20T05:24:15Z","createdBy":"6368c8a6b397bb7ad67fde5b"},
{"company":"Bartell, Buckridge and Moen","position":"Product Engineer","status":"selected","offer":10,"jobType":"Full-Time","jobLocation":"Shijiao","createdAt":"2022-02-17T10:38:16Z","createdBy":"6368c8a6b397bb7ad67fde5b"},
{"company":"Gusikowski-Ziemann","position":"Account Coordinator","status":"interview","offer":29,"jobType":"Full-Time","jobLocation":"Lazarevac","createdAt":"2022-10-13T04:48:52Z","createdBy":"6368c8a6b397bb7ad67fde5b"},
{"company":"Anderson-Effertz","position":"Research Assistant III","status":"pending","offer":29,"jobType":"Full-Time","jobLocation":"Carpenter","createdAt":"2022-05-12T08:32:44Z","createdBy":"6368c8a6b397bb7ad67fde5b"},
{"company":"Borer, Cronin and Swift","position":"Structural Analysis Engineer","status":"declined","offer":10,"jobType":"Full-Time","jobLocation":"Bondoboghila","createdAt":"2022-07-25T15:41:28Z","createdBy":"6368c8a6b397bb7ad67fde5b"},
{"company":"Funk-Baumbach","position":"Biostatistician III","status":"declined","offer":19,"jobType":"Full-Time + Internship","jobLocation":"Brodósqui","createdAt":"2022-10-23T02:32:05Z","createdBy":"6368c8a6b397bb7ad67fde5b"},
{"company":"Beier Inc","position":"Web Designer II","status":"pending","offer":28,"jobType":"Internship","jobLocation":"Changgang","createdAt":"2022-09-24T15:38:59Z","createdBy":"6368c8a6b397bb7ad67fde5b"},
{"company":"Maggio-Bruen","position":"Software Consultant","status":"declined","offer":16,"jobType":"Full-Time + Internship","jobLocation":"Gaoqiaolou","createdAt":"2022-07-08T21:54:41Z","createdBy":"6368c8a6b397bb7ad67fde5b"},
{"company":"Skiles-Huel","position":"Analyst Programmer","status":"declined","offer":30,"jobType":"Internship","jobLocation":"Göteborg","createdAt":"2022-01-28T13:37:44Z","createdBy":"6368c8a6b397bb7ad67fde5b"},
{"company":"Pfeffer, Auer and Keebler","position":"Assistant Manager","status":"interview","offer":4,"jobType":"Internship","jobLocation":"Luso","createdAt":"2022-04-14T11:23:08Z","createdBy":"6368c8a6b397bb7ad67fde5b"},
{"company":"Buckridge-Kertzmann","position":"Business Systems Development Analyst","status":"pending","offer":19,"jobType":"Full-Time + Internship","jobLocation":"Aksha","createdAt":"2022-08-22T06:49:31Z","createdBy":"6368c8a6b397bb7ad67fde5b"},
{"company":"Moen Group","position":"Recruiter","status":"declined","offer":26,"jobType":"Full-Time","jobLocation":"Vila do Maio","createdAt":"2022-03-11T08:25:49Z","createdBy":"6368c8a6b397bb7ad67fde5b"}]